badlands_doe_toolset/__init__.py
badlands_doe_toolset/badlands_multiproc_run.py
badlands_doe_toolset/csv_to_badlands.py
badlands_doe_toolset/postproc_utils.py
badlands_doe_toolset/postproc_xmf_update.py
badlands_doe_toolset/well_doe_similarity.py
badlands_doe_toolset/well_doe_similarity_experimental.py
badlands_doe_toolset-0.1.5.dist-info/LICENSE
badlands_doe_toolset-0.1.5.dist-info/METADATA
badlands_doe_toolset-0.1.5.dist-info/WHEEL
badlands_doe_toolset-0.1.5.dist-info/top_level.txt
badlands_doe_toolset-0.1.5.dist-info/RECORD
